wattrex_driver_epc/__init__.py
wattrex_driver_epc/__version__.py
wattrex_driver_epc/context.py
wattrex_driver_epc/drv_epc_common.py
wattrex_driver_epc/drv_epc_device.py
wattrex_driver_epc-0.0.9.dist-info/LICENSE.txt
wattrex_driver_epc-0.0.9.dist-info/METADATA
wattrex_driver_epc-0.0.9.dist-info/WHEEL
wattrex_driver_epc-0.0.9.dist-info/top_level.txt
wattrex_driver_epc-0.0.9.dist-info/RECORD
