Metadata-Version: 2.1
Name: wattrex-driver-epc
Version: 0.0.9
Summary: Driver to control the EPC in an easy way through can bus.
Author-email: Roberto Aldea <r.aldea.csic+pypi@gmail.com>, Marius Crisan <mariuscrsn+pypi@gmail.com>, Pablo Pastor <pastorpflores+pypi@gmail.com>, Javier Sanz <javiersanzmoline@gmail.com>, Luis Roche <luis.roche@hotmail.com>
License: GNU GENERAL PUBLIC LICENSE
Project-URL: Homepage, https://github.com/WattRex/Battery-Cycler-Drivers
Project-URL: Bug Reports, https://github.com/WattRex/Battery-Cycler-Drivers/issues
Project-URL: Bug Tracker, https://github.com/WattRex/Battery-Cycler-Drivers/issues
Project-URL: Source, https://github.com/WattRex/Battery-Cycler-Drivers/code/drv/drv_epc
Project-URL: Funding, https://donate.pypi.org
Keywords: CANBus,Embedded Systems,Power Control,PID,EPC,Electronic Power Control
Classifier: Development Status :: 3 - Alpha
Classifier: Topic :: Software Development :: Embedded Systems
Classifier: Operating System :: OS Independent
Classifier: License :: OSI Approved :: GNU Affero General Public License v3
Classifier: Programming Language :: Python :: 3
Classifier: Programming Language :: Python :: 3.7
Classifier: Programming Language :: Python :: 3.8
Classifier: Programming Language :: Python :: 3.9
Classifier: Programming Language :: Python :: 3.10
Classifier: Programming Language :: Python :: 3.11
Classifier: Programming Language :: Python :: 3 :: Only
Requires-Python: >=3.7
License-File: LICENSE.txt
Requires-Dist: bitarray >=2.8.1
Requires-Dist: can-sniffer >=0.0.6
Requires-Dist: pytz >=2023.3
Requires-Dist: system-logger-tool >=0.0.3
Requires-Dist: system-shared-tool >=0.2.5
